CBOD/MMLU_Eval.py
CBOD/__init__.py
CBOD/mmlu_rephrase_DS.py
CBOD-0.4.0.dist-info/METADATA
CBOD-0.4.0.dist-info/WHEEL
CBOD-0.4.0.dist-info/top_level.txt
CBOD-0.4.0.dist-info/RECORD
