Metadata-Version: 2.2
Name: CBOD
Version: 0.4.0
Summary: A short description of your package
Home-page: https://github.com/SeffiCohen/CBOD
Author: Seffi Cohen
Author-email: seffi@post.bgu.ac.il
Classifier: Programming Language :: Python :: 3
Classifier: License :: OSI Approved :: MIT License
Classifier: Operating System :: OS Independent
Requires-Python: >=3.6
Requires-Dist: torch>=1.10.0
Requires-Dist: transformers>=4.25.0
Requires-Dist: tqdm>=4.60.0
Requires-Dist: requests>=2.25.0
Requires-Dist: datasets>=2.0.0
Dynamic: author
Dynamic: author-email
Dynamic: classifier
Dynamic: description
Dynamic: description-content-type
Dynamic: home-page
Dynamic: requires-dist
Dynamic: requires-python
Dynamic: summary
